{
  "animations": {
    "Antic": {
      "sprites": [
        {
          "name": "Crypt Worm Anim/Antic/Antic_0000.png",
          "atlasGUID": "172fb1721a80e99479ba9fddfca5c666",
          "x": 113,
          "y": 760,
          "w": 127,
          "h": 113,
          "rotated": false,
          "isDuplicate": false,
          "duplicateOf": "",
          "trimmedW": 127,
          "trimmedH": 113,
          "trimmedX": 76,
          "trimmedY": 7,
          "untrimmedW": 308,
          "untrimmedH": 245
        },
        {
          "name": "Crypt Worm Anim/Antic/Antic_0001.png",
          "atlasGUID": "172fb1721a80e99479ba9fddfca5c666",
          "x": 784,
          "y": 519,
          "w": 149,
          "h": 105,
          "rotated": false,
          "isDuplicate": false,
          "duplicateOf": "",
          "trimmedW": 149,
          "trimmedH": 105,
          "trimmedX": 68,
          "trimmedY": 12,
          "untrimmedW": 308,
          "untrimmedH": 245
        },
        {
          "name": "Crypt Worm Anim/Antic/Antic_0002.png",
          "atlasGUID": "172fb1721a80e99479ba9fddfca5c666",
          "x": 251,
          "y": 679,
          "w": 143,
          "h": 105,
          "rotated": false,
          "isDuplicate": false,
          "duplicateOf": "",
          "trimmedW": 143,
          "trimmedH": 105,
          "trimmedX": 70,
          "trimmedY": 11,
          "untrimmedW": 308,
          "untrimmedH": 245
        },
        {
          "name": "Crypt Worm Anim/Antic/Antic_0003.png",
          "atlasGUID": "172fb1721a80e99479ba9fddfca5c666",
          "x": 918,
          "y": 647,
          "w": 99,
          "h": 140,
          "rotated": true,
          "isDuplicate": false,
          "duplicateOf": "",
          "trimmedW": 140,
          "trimmedH": 99,
          "trimmedX": 75,
          "trimmedY": 11,
          "untrimmedW": 308,
          "untrimmedH": 245
        }
      ]
    },
    "Leap": {
      "sprites": [
        {
          "name": "Crypt Worm Anim/Leap/Leap_0000.png",
          "atlasGUID": "172fb1721a80e99479ba9fddfca5c666",
          "x": 520,
          "y": 338,
          "w": 124,
          "h": 156,
          "rotated": true,
          "isDuplicate": false,
          "duplicateOf": "",
          "trimmedW": 156,
          "trimmedH": 124,
          "trimmedX": 85,
          "trimmedY": 10,
          "untrimmedW": 308,
          "untrimmedH": 245
        },
        {
          "name": "Crypt Worm Anim/Leap/Leap_0001.png",
          "atlasGUID": "172fb1721a80e99479ba9fddfca5c666",
          "x": 649,
          "y": 260,
          "w": 156,
          "h": 126,
          "rotated": false,
          "isDuplicate": false,
          "duplicateOf": "",
          "trimmedW": 156,
          "trimmedH": 126,
          "trimmedX": 85,
          "trimmedY": 4,
          "untrimmedW": 308,
          "untrimmedH": 245
        },
        {
          "name": "Crypt Worm Anim/Leap/Leap_0002.png",
          "atlasGUID": "172fb1721a80e99479ba9fddfca5c666",
          "x": 858,
          "y": 144,
          "w": 157,
          "h": 132,
          "rotated": false,
          "isDuplicate": false,
          "duplicateOf": "",
          "trimmedW": 157,
          "trimmedH": 132,
          "trimmedX": 84,
          "trimmedY": 9,
          "untrimmedW": 308,
          "untrimmedH": 245
        }
      ]
    },
    "Land": {
      "sprites": [
        {
          "name": "Crypt Worm Anim/Land/Land_0000.png",
          "atlasGUID": "172fb1721a80e99479ba9fddfca5c666",
          "x": 622,
          "y": 517,
          "w": 158,
          "h": 100,
          "rotated": false,
          "isDuplicate": false,
          "duplicateOf": "",
          "trimmedW": 158,
          "trimmedH": 100,
          "trimmedX": 78,
          "trimmedY": 12,
          "untrimmedW": 308,
          "untrimmedH": 245
        },
        {
          "name": "Crypt Worm Anim/Land/Land_0001_dup_Antic_0001.png",
          "atlasGUID": "172fb1721a80e99479ba9fddfca5c666",
          "x": 784,
          "y": 519,
          "w": 149,
          "h": 105,
          "rotated": false,
          "isDuplicate": true,
          "duplicateOf": "Crypt Worm Anim/Antic/Antic_0001.png",
          "trimmedW": 149,
          "trimmedH": 105,
          "trimmedX": 68,
          "trimmedY": 12,
          "untrimmedW": 308,
          "untrimmedH": 245
        },
        {
          "name": "Crypt Worm Anim/Land/Land_0002_dup_Antic_0000.png",
          "atlasGUID": "172fb1721a80e99479ba9fddfca5c666",
          "x": 113,
          "y": 760,
          "w": 127,
          "h": 113,
          "rotated": false,
          "isDuplicate": true,
          "duplicateOf": "Crypt Worm Anim/Antic/Antic_0000.png",
          "trimmedW": 127,
          "trimmedH": 113,
          "trimmedX": 76,
          "trimmedY": 7,
          "untrimmedW": 308,
          "untrimmedH": 245
        }
      ]
    },
    "Crawl": {
      "sprites": [
        {
          "name": "Crypt Worm Anim/Crawl/Crawl_0000.png",
          "atlasGUID": "172fb1721a80e99479ba9fddfca5c666",
          "x": 768,
          "y": 740,
          "w": 128,
          "h": 108,
          "rotated": false,
          "isDuplicate": false,
          "duplicateOf": "",
          "trimmedW": 128,
          "trimmedH": 108,
          "trimmedX": 102,
          "trimmedY": 15,
          "untrimmedW": 308,
          "untrimmedH": 245
        },
        {
          "name": "Crypt Worm Anim/Crawl/Crawl_0001.png",
          "atlasGUID": "172fb1721a80e99479ba9fddfca5c666",
          "x": 802,
          "y": 411,
          "w": 158,
          "h": 104,
          "rotated": false,
          "isDuplicate": false,
          "duplicateOf": "",
          "trimmedW": 158,
          "trimmedH": 104,
          "trimmedX": 83,
          "trimmedY": 15,
          "untrimmedW": 308,
          "untrimmedH": 245
        },
        {
          "name": "Crypt Worm Anim/Crawl/Crawl_0002.png",
          "atlasGUID": "172fb1721a80e99479ba9fddfca5c666",
          "x": 2,
          "y": 608,
          "w": 107,
          "h": 166,
          "rotated": true,
          "isDuplicate": false,
          "duplicateOf": "",
          "trimmedW": 166,
          "trimmedH": 107,
          "trimmedX": 79,
          "trimmedY": 15,
          "untrimmedW": 308,
          "untrimmedH": 245
        },
        {
          "name": "Crypt Worm Anim/Crawl/Crawl_0003.png",
          "atlasGUID": "172fb1721a80e99479ba9fddfca5c666",
          "x": 301,
          "y": 430,
          "w": 175,
          "h": 110,
          "rotated": false,
          "isDuplicate": false,
          "duplicateOf": "",
          "trimmedW": 175,
          "trimmedH": 110,
          "trimmedX": 73,
          "trimmedY": 15,
          "untrimmedW": 308,
          "untrimmedH": 245
        },
        {
          "name": "Crypt Worm Anim/Crawl/Crawl_0004.png",
          "atlasGUID": "172fb1721a80e99479ba9fddfca5c666",
          "x": 771,
          "y": 628,
          "w": 143,
          "h": 108,
          "rotated": false,
          "isDuplicate": false,
          "duplicateOf": "",
          "trimmedW": 143,
          "trimmedH": 108,
          "trimmedX": 90,
          "trimmedY": 13,
          "untrimmedW": 308,
          "untrimmedH": 245
        }
      ]
    },
    "Death Air": {
      "sprites": [
        {
          "name": "Crypt Worm Anim/Death Air/Death Air_0000.png",
          "atlasGUID": "172fb1721a80e99479ba9fddfca5c666",
          "x": 2,
          "y": 297,
          "w": 155,
          "h": 133,
          "rotated": true,
          "isDuplicate": false,
          "duplicateOf": "",
          "trimmedW": 133,
          "trimmedH": 155,
          "trimmedX": 85,
          "trimmedY": 9,
          "untrimmedW": 308,
          "untrimmedH": 245
        },
        {
          "name": "Crypt Worm Anim/Death Air/Death Air_0001.png",
          "atlasGUID": "172fb1721a80e99479ba9fddfca5c666",
          "x": 352,
          "y": 165,
          "w": 165,
          "h": 130,
          "rotated": true,
          "isDuplicate": false,
          "duplicateOf": "",
          "trimmedW": 130,
          "trimmedH": 165,
          "trimmedX": 82,
          "trimmedY": 2,
          "untrimmedW": 308,
          "untrimmedH": 245
        },
        {
          "name": "Crypt Worm Anim/Death Air/Death Air_0002.png",
          "atlasGUID": "172fb1721a80e99479ba9fddfca5c666",
          "x": 857,
          "y": 280,
          "w": 152,
          "h": 127,
          "rotated": true,
          "isDuplicate": false,
          "duplicateOf": "",
          "trimmedW": 127,
          "trimmedH": 152,
          "trimmedX": 86,
          "trimmedY": 12,
          "untrimmedW": 308,
          "untrimmedH": 245
        }
      ]
    },
    "Death Roll": {
      "sprites": [
        {
          "name": "Crypt Worm Anim/Death Roll/Death Roll_0000.png",
          "atlasGUID": "172fb1721a80e99479ba9fddfca5c666",
          "x": 522,
          "y": 2,
          "w": 154,
          "h": 153,
          "rotated": true,
          "isDuplicate": false,
          "duplicateOf": "",
          "trimmedW": 153,
          "trimmedH": 154,
          "trimmedX": 77,
          "trimmedY": 10,
          "untrimmedW": 308,
          "untrimmedH": 245
        },
        {
          "name": "Crypt Worm Anim/Death Roll/Death Roll_0001.png",
          "atlasGUID": "172fb1721a80e99479ba9fddfca5c666",
          "x": 352,
          "y": 2,
          "w": 166,
          "h": 159,
          "rotated": false,
          "isDuplicate": false,
          "duplicateOf": "",
          "trimmedW": 166,
          "trimmedH": 159,
          "trimmedX": 66,
          "trimmedY": 0,
          "untrimmedW": 308,
          "untrimmedH": 245
        },
        {
          "name": "Crypt Worm Anim/Death Roll/Death Roll_0002.png",
          "atlasGUID": "172fb1721a80e99479ba9fddfca5c666",
          "x": 184,
          "y": 2,
          "w": 164,
          "h": 162,
          "rotated": false,
          "isDuplicate": false,
          "duplicateOf": "",
          "trimmedW": 164,
          "trimmedH": 162,
          "trimmedX": 78,
          "trimmedY": 0,
          "untrimmedW": 308,
          "untrimmedH": 245
        },
        {
          "name": "Crypt Worm Anim/Death Roll/Death Roll_0003.png",
          "atlasGUID": "172fb1721a80e99479ba9fddfca5c666",
          "x": 2,
          "y": 2,
          "w": 178,
          "h": 169,
          "rotated": false,
          "isDuplicate": false,
          "duplicateOf": "",
          "trimmedW": 178,
          "trimmedH": 169,
          "trimmedX": 67,
          "trimmedY": 0,
          "untrimmedW": 308,
          "untrimmedH": 245
        }
      ]
    },
    "Death Land": {
      "sprites": [
        {
          "name": "Crypt Worm Anim/Death Land/Death Land_0000.png",
          "atlasGUID": "172fb1721a80e99479ba9fddfca5c666",
          "x": 522,
          "y": 159,
          "w": 123,
          "h": 175,
          "rotated": true,
          "isDuplicate": false,
          "duplicateOf": "",
          "trimmedW": 175,
          "trimmedH": 123,
          "trimmedX": 56,
          "trimmedY": 8,
          "untrimmedW": 308,
          "untrimmedH": 245
        },
        {
          "name": "Crypt Worm Anim/Death Land/Death Land_0001.png",
          "atlasGUID": "172fb1721a80e99479ba9fddfca5c666",
          "x": 2,
          "y": 434,
          "w": 117,
          "h": 170,
          "rotated": true,
          "isDuplicate": false,
          "duplicateOf": "",
          "trimmedW": 170,
          "trimmedH": 117,
          "trimmedX": 61,
          "trimmedY": 12,
          "untrimmedW": 308,
          "untrimmedH": 245
        },
        {
          "name": "Crypt Worm Anim/Death Land/Death Land_0002.png",
          "atlasGUID": "172fb1721a80e99479ba9fddfca5c666",
          "x": 2,
          "y": 175,
          "w": 175,
          "h": 118,
          "rotated": false,
          "isDuplicate": false,
          "duplicateOf": "",
          "trimmedW": 175,
          "trimmedH": 118,
          "trimmedX": 62,
          "trimmedY": 8,
          "untrimmedW": 308,
          "untrimmedH": 245
        }
      ]
    },
    "Dig Appear": {
      "sprites": [
        {
          "name": "Crypt Worm Anim/Dig Appear/Dig Appear_0000.png",
          "atlasGUID": "172fb1721a80e99479ba9fddfca5c666",
          "x": 937,
          "y": 519,
          "w": 75,
          "h": 124,
          "rotated": true,
          "isDuplicate": false,
          "duplicateOf": "",
          "trimmedW": 124,
          "trimmedH": 75,
          "trimmedX": 102,
          "trimmedY": 0,
          "untrimmedW": 322,
          "untrimmedH": 273
        },
        {
          "name": "Crypt Worm Anim/Dig Appear/Dig Appear_0001.png",
          "atlasGUID": "172fb1721a80e99479ba9fddfca5c666",
          "x": 568,
          "y": 732,
          "w": 121,
          "h": 118,
          "rotated": false,
          "isDuplicate": false,
          "duplicateOf": "",
          "trimmedW": 121,
          "trimmedH": 118,
          "trimmedX": 87,
          "trimmedY": 0,
          "untrimmedW": 322,
          "untrimmedH": 273
        },
        {
          "name": "Crypt Worm Anim/Dig Appear/Dig Appear_0002.png",
          "atlasGUID": "172fb1721a80e99479ba9fddfca5c666",
          "x": 113,
          "y": 623,
          "w": 134,
          "h": 133,
          "rotated": true,
          "isDuplicate": false,
          "duplicateOf": "",
          "trimmedW": 133,
          "trimmedH": 134,
          "trimmedX": 91,
          "trimmedY": 0,
          "untrimmedW": 322,
          "untrimmedH": 273
        },
        {
          "name": "Crypt Worm Anim/Dig Appear/Dig Appear_0003.png",
          "atlasGUID": "172fb1721a80e99479ba9fddfca5c666",
          "x": 648,
          "y": 390,
          "w": 150,
          "h": 123,
          "rotated": true,
          "isDuplicate": false,
          "duplicateOf": "",
          "trimmedW": 123,
          "trimmedH": 150,
          "trimmedX": 110,
          "trimmedY": 4,
          "untrimmedW": 322,
          "untrimmedH": 273
        },
        {
          "name": "Crypt Worm Anim/Dig Appear/Dig Appear_0004.png",
          "atlasGUID": "172fb1721a80e99479ba9fddfca5c666",
          "x": 123,
          "y": 495,
          "w": 151,
          "h": 124,
          "rotated": true,
          "isDuplicate": false,
          "duplicateOf": "",
          "trimmedW": 124,
          "trimmedH": 151,
          "trimmedX": 102,
          "trimmedY": 8,
          "untrimmedW": 322,
          "untrimmedH": 273
        },
        {
          "name": "Crypt Worm Anim/Dig Appear/Dig Appear_0005.png",
          "atlasGUID": "172fb1721a80e99479ba9fddfca5c666",
          "x": 480,
          "y": 498,
          "w": 138,
          "h": 133,
          "rotated": true,
          "isDuplicate": false,
          "duplicateOf": "",
          "trimmedW": 133,
          "trimmedH": 138,
          "trimmedX": 99,
          "trimmedY": 15,
          "untrimmedW": 322,
          "untrimmedH": 273
        }
      ]
    },
    "Dig Away": {
      "sprites": [
        {
          "name": "Crypt Worm Anim/Dig Away/Dig Away_0000.png",
          "atlasGUID": "172fb1721a80e99479ba9fddfca5c666",
          "x": 161,
          "y": 344,
          "w": 136,
          "h": 147,
          "rotated": true,
          "isDuplicate": false,
          "duplicateOf": "",
          "trimmedW": 147,
          "trimmedH": 136,
          "trimmedX": 102,
          "trimmedY": 5,
          "untrimmedW": 308,
          "untrimmedH": 245
        },
        {
          "name": "Crypt Worm Anim/Dig Away/Dig Away_0001.png",
          "atlasGUID": "172fb1721a80e99479ba9fddfca5c666",
          "x": 184,
          "y": 168,
          "w": 121,
          "h": 172,
          "rotated": true,
          "isDuplicate": false,
          "duplicateOf": "",
          "trimmedW": 172,
          "trimmedH": 121,
          "trimmedX": 79,
          "trimmedY": 15,
          "untrimmedW": 308,
          "untrimmedH": 245
        },
        {
          "name": "Crypt Worm Anim/Dig Away/Dig Away_0002.png",
          "atlasGUID": "172fb1721a80e99479ba9fddfca5c666",
          "x": 278,
          "y": 544,
          "w": 137,
          "h": 131,
          "rotated": false,
          "isDuplicate": false,
          "duplicateOf": "",
          "trimmedW": 137,
          "trimmedH": 131,
          "trimmedX": 99,
          "trimmedY": 0,
          "untrimmedW": 308,
          "untrimmedH": 245
        },
        {
          "name": "Crypt Worm Anim/Dig Away/Dig Away_0003.png",
          "atlasGUID": "172fb1721a80e99479ba9fddfca5c666",
          "x": 805,
          "y": 909,
          "w": 118,
          "h": 94,
          "rotated": false,
          "isDuplicate": false,
          "duplicateOf": "",
          "trimmedW": 118,
          "trimmedH": 94,
          "trimmedX": 109,
          "trimmedY": 0,
          "untrimmedW": 308,
          "untrimmedH": 245
        },
        {
          "name": "Crypt Worm Anim/Dig Away/Dig Away_0004.png",
          "atlasGUID": "172fb1721a80e99479ba9fddfca5c666",
          "x": 476,
          "y": 299,
          "w": 40,
          "h": 64,
          "rotated": true,
          "isDuplicate": false,
          "duplicateOf": "",
          "trimmedW": 64,
          "trimmedH": 40,
          "trimmedX": 121,
          "trimmedY": 0,
          "untrimmedW": 308,
          "untrimmedH": 245
        }
      ]
    },
    "Turn": {
      "sprites": [
        {
          "name": "Crypt Worm Anim/Turn/Turn_0000.png",
          "atlasGUID": "172fb1721a80e99479ba9fddfca5c666",
          "x": 419,
          "y": 635,
          "w": 145,
          "h": 105,
          "rotated": false,
          "isDuplicate": false,
          "duplicateOf": "",
          "trimmedW": 145,
          "trimmedH": 105,
          "trimmedX": 88,
          "trimmedY": 13,
          "untrimmedW": 308,
          "untrimmedH": 245
        },
        {
          "name": "Crypt Worm Anim/Turn/Turn_0001.png",
          "atlasGUID": "172fb1721a80e99479ba9fddfca5c666",
          "x": 693,
          "y": 852,
          "w": 108,
          "h": 116,
          "rotated": true,
          "isDuplicate": false,
          "duplicateOf": "",
          "trimmedW": 116,
          "trimmedH": 108,
          "trimmedX": 110,
          "trimmedY": 10,
          "untrimmedW": 308,
          "untrimmedH": 245
        },
        {
          "name": "Crypt Worm Anim/Turn/Turn_0002.png",
          "atlasGUID": "172fb1721a80e99479ba9fddfca5c666",
          "x": 622,
          "y": 621,
          "w": 145,
          "h": 107,
          "rotated": false,
          "isDuplicate": false,
          "duplicateOf": "",
          "trimmedW": 145,
          "trimmedH": 107,
          "trimmedX": 90,
          "trimmedY": 12,
          "untrimmedW": 308,
          "untrimmedH": 245
        }
      ]
    },
    "TurnToCrawl": {
      "sprites": [
        {
          "name": "Crypt Worm Anim/TurnToCrawl/TurnToCrawl_0000_dup_Turn_0000.png",
          "atlasGUID": "172fb1721a80e99479ba9fddfca5c666",
          "x": 419,
          "y": 635,
          "w": 145,
          "h": 105,
          "rotated": false,
          "isDuplicate": true,
          "duplicateOf": "Crypt Worm Anim/Turn/Turn_0000.png",
          "trimmedW": 145,
          "trimmedH": 105,
          "trimmedX": 88,
          "trimmedY": 13,
          "untrimmedW": 308,
          "untrimmedH": 245
        },
        {
          "name": "Crypt Worm Anim/TurnToCrawl/TurnToCrawl_0001_dup_Turn_0001.png",
          "atlasGUID": "172fb1721a80e99479ba9fddfca5c666",
          "x": 693,
          "y": 852,
          "w": 108,
          "h": 116,
          "rotated": true,
          "isDuplicate": true,
          "duplicateOf": "Crypt Worm Anim/Turn/Turn_0001.png",
          "trimmedW": 116,
          "trimmedH": 108,
          "trimmedX": 110,
          "trimmedY": 10,
          "untrimmedW": 308,
          "untrimmedH": 245
        },
        {
          "name": "Crypt Worm Anim/TurnToCrawl/TurnToCrawl_0002_dup_Turn_0002.png",
          "atlasGUID": "172fb1721a80e99479ba9fddfca5c666",
          "x": 622,
          "y": 621,
          "w": 145,
          "h": 107,
          "rotated": false,
          "isDuplicate": true,
          "duplicateOf": "Crypt Worm Anim/Turn/Turn_0002.png",
          "trimmedW": 145,
          "trimmedH": 107,
          "trimmedX": 90,
          "trimmedY": 12,
          "untrimmedW": 308,
          "untrimmedH": 245
        },
        {
          "name": "Crypt Worm Anim/TurnToCrawl/TurnToCrawl_0003_dup_Crawl_0000.png",
          "atlasGUID": "172fb1721a80e99479ba9fddfca5c666",
          "x": 768,
          "y": 740,
          "w": 128,
          "h": 108,
          "rotated": false,
          "isDuplicate": true,
          "duplicateOf": "Crypt Worm Anim/Crawl/Crawl_0000.png",
          "trimmedW": 128,
          "trimmedH": 108,
          "trimmedX": 102,
          "trimmedY": 15,
          "untrimmedW": 308,
          "untrimmedH": 245
        },
        {
          "name": "Crypt Worm Anim/TurnToCrawl/TurnToCrawl_0004_dup_Crawl_0001.png",
          "atlasGUID": "172fb1721a80e99479ba9fddfca5c666",
          "x": 802,
          "y": 411,
          "w": 158,
          "h": 104,
          "rotated": false,
          "isDuplicate": true,
          "duplicateOf": "Crypt Worm Anim/Crawl/Crawl_0001.png",
          "trimmedW": 158,
          "trimmedH": 104,
          "trimmedX": 83,
          "trimmedY": 15,
          "untrimmedW": 308,
          "untrimmedH": 245
        },
        {
          "name": "Crypt Worm Anim/TurnToCrawl/TurnToCrawl_0005_dup_Crawl_0002.png",
          "atlasGUID": "172fb1721a80e99479ba9fddfca5c666",
          "x": 2,
          "y": 608,
          "w": 107,
          "h": 166,
          "rotated": true,
          "isDuplicate": true,
          "duplicateOf": "Crypt Worm Anim/Crawl/Crawl_0002.png",
          "trimmedW": 166,
          "trimmedH": 107,
          "trimmedX": 79,
          "trimmedY": 15,
          "untrimmedW": 308,
          "untrimmedH": 245
        },
        {
          "name": "Crypt Worm Anim/TurnToCrawl/TurnToCrawl_0006_dup_Crawl_0003.png",
          "atlasGUID": "172fb1721a80e99479ba9fddfca5c666",
          "x": 301,
          "y": 430,
          "w": 175,
          "h": 110,
          "rotated": false,
          "isDuplicate": true,
          "duplicateOf": "Crypt Worm Anim/Crawl/Crawl_0003.png",
          "trimmedW": 175,
          "trimmedH": 110,
          "trimmedX": 73,
          "trimmedY": 15,
          "untrimmedW": 308,
          "untrimmedH": 245
        },
        {
          "name": "Crypt Worm Anim/TurnToCrawl/TurnToCrawl_0007_dup_Crawl_0004.png",
          "atlasGUID": "172fb1721a80e99479ba9fddfca5c666",
          "x": 771,
          "y": 628,
          "w": 143,
          "h": 108,
          "rotated": false,
          "isDuplicate": true,
          "duplicateOf": "Crypt Worm Anim/Crawl/Crawl_0004.png",
          "trimmedW": 143,
          "trimmedH": 108,
          "trimmedX": 90,
          "trimmedY": 13,
          "untrimmedW": 308,
          "untrimmedH": 245
        }
      ]
    },
    "Dig Leap Antic": {
      "sprites": [
        {
          "name": "Crypt Worm Anim/Dig Leap Antic/Dig Leap Antic_0000_dup_Dig Appear_0001.png",
          "atlasGUID": "172fb1721a80e99479ba9fddfca5c666",
          "x": 568,
          "y": 732,
          "w": 121,
          "h": 118,
          "rotated": false,
          "isDuplicate": true,
          "duplicateOf": "Crypt Worm Anim/Dig Appear/Dig Appear_0001.png",
          "trimmedW": 121,
          "trimmedH": 118,
          "trimmedX": 87,
          "trimmedY": 0,
          "untrimmedW": 322,
          "untrimmedH": 273
        }
      ]
    },
    "Chomp": {
      "sprites": [
        {
          "name": "Crypt Worm Anim/Chomp/Chomp_0000.png",
          "atlasGUID": "172fb1721a80e99479ba9fddfca5c666",
          "x": 861,
          "y": 2,
          "w": 159,
          "h": 138,
          "rotated": true,
          "isDuplicate": false,
          "duplicateOf": "",
          "trimmedW": 138,
          "trimmedH": 159,
          "trimmedX": 109,
          "trimmedY": 25,
          "untrimmedW": 308,
          "untrimmedH": 245
        },
        {
          "name": "Crypt Worm Anim/Chomp/Chomp_0001.png",
          "atlasGUID": "172fb1721a80e99479ba9fddfca5c666",
          "x": 680,
          "y": 130,
          "w": 174,
          "h": 126,
          "rotated": false,
          "isDuplicate": false,
          "duplicateOf": "",
          "trimmedW": 174,
          "trimmedH": 126,
          "trimmedX": 93,
          "trimmedY": 27,
          "untrimmedW": 308,
          "untrimmedH": 245
        },
        {
          "name": "Crypt Worm Anim/Chomp/Chomp_0002.png",
          "atlasGUID": "172fb1721a80e99479ba9fddfca5c666",
          "x": 680,
          "y": 2,
          "w": 177,
          "h": 124,
          "rotated": false,
          "isDuplicate": false,
          "duplicateOf": "",
          "trimmedW": 177,
          "trimmedH": 124,
          "trimmedX": 92,
          "trimmedY": 33,
          "untrimmedW": 308,
          "untrimmedH": 245
        }
      ]
    },
    "Chomp Rebound": {
      "sprites": [
        {
          "name": "Crypt Worm Anim/Chomp Rebound/Chomp Rebound_0000.png",
          "atlasGUID": "172fb1721a80e99479ba9fddfca5c666",
          "x": 309,
          "y": 299,
          "w": 163,
          "h": 127,
          "rotated": true,
          "isDuplicate": false,
          "duplicateOf": "",
          "trimmedW": 127,
          "trimmedH": 163,
          "trimmedX": 91,
          "trimmedY": 8,
          "untrimmedW": 308,
          "untrimmedH": 245
        },
        {
          "name": "Crypt Worm Anim/Chomp Rebound/Chomp Rebound_0001_dup_Death Roll_0000.png",
          "atlasGUID": "172fb1721a80e99479ba9fddfca5c666",
          "x": 522,
          "y": 2,
          "w": 154,
          "h": 153,
          "rotated": true,
          "isDuplicate": true,
          "duplicateOf": "Crypt Worm Anim/Death Roll/Death Roll_0000.png",
          "trimmedW": 153,
          "trimmedH": 154,
          "trimmedX": 77,
          "trimmedY": 10,
          "untrimmedW": 308,
          "untrimmedH": 245
        },
        {
          "name": "Crypt Worm Anim/Chomp Rebound/Chomp Rebound_0002_dup_Death Roll_0001.png",
          "atlasGUID": "172fb1721a80e99479ba9fddfca5c666",
          "x": 352,
          "y": 2,
          "w": 166,
          "h": 159,
          "rotated": false,
          "isDuplicate": true,
          "duplicateOf": "Crypt Worm Anim/Death Roll/Death Roll_0001.png",
          "trimmedW": 166,
          "trimmedH": 159,
          "trimmedX": 66,
          "trimmedY": 0,
          "untrimmedW": 308,
          "untrimmedH": 245
        },
        {
          "name": "Crypt Worm Anim/Chomp Rebound/Chomp Rebound_0003_dup_Death Roll_0002.png",
          "atlasGUID": "172fb1721a80e99479ba9fddfca5c666",
          "x": 184,
          "y": 2,
          "w": 164,
          "h": 162,
          "rotated": false,
          "isDuplicate": true,
          "duplicateOf": "Crypt Worm Anim/Death Roll/Death Roll_0002.png",
          "trimmedW": 164,
          "trimmedH": 162,
          "trimmedX": 78,
          "trimmedY": 0,
          "untrimmedW": 308,
          "untrimmedH": 245
        }
      ]
    },
    "Sing": {
      "sprites": [
        {
          "name": "Crypt Worm Anim/Sing/Sing_0000_dup_Land_0000.png",
          "atlasGUID": "172fb1721a80e99479ba9fddfca5c666",
          "x": 622,
          "y": 517,
          "w": 158,
          "h": 100,
          "rotated": false,
          "isDuplicate": true,
          "duplicateOf": "Crypt Worm Anim/Land/Land_0000.png",
          "trimmedW": 158,
          "trimmedH": 100,
          "trimmedX": 78,
          "trimmedY": 12,
          "untrimmedW": 308,
          "untrimmedH": 245
        },
        {
          "name": "Crypt Worm Anim/Sing/Sing_0001_dup_Leap_0000.png",
          "atlasGUID": "172fb1721a80e99479ba9fddfca5c666",
          "x": 520,
          "y": 338,
          "w": 124,
          "h": 156,
          "rotated": true,
          "isDuplicate": true,
          "duplicateOf": "Crypt Worm Anim/Leap/Leap_0000.png",
          "trimmedW": 156,
          "trimmedH": 124,
          "trimmedX": 85,
          "trimmedY": 10,
          "untrimmedW": 308,
          "untrimmedH": 245
        },
        {
          "name": "Crypt Worm Anim/Sing/Sing_0002_dup_Leap_0001.png",
          "atlasGUID": "172fb1721a80e99479ba9fddfca5c666",
          "x": 649,
          "y": 260,
          "w": 156,
          "h": 126,
          "rotated": false,
          "isDuplicate": true,
          "duplicateOf": "Crypt Worm Anim/Leap/Leap_0001.png",
          "trimmedW": 156,
          "trimmedH": 126,
          "trimmedX": 85,
          "trimmedY": 4,
          "untrimmedW": 308,
          "untrimmedH": 245
        },
        {
          "name": "Crypt Worm Anim/Sing/Sing_0003_dup_Leap_0002.png",
          "atlasGUID": "172fb1721a80e99479ba9fddfca5c666",
          "x": 858,
          "y": 144,
          "w": 157,
          "h": 132,
          "rotated": false,
          "isDuplicate": true,
          "duplicateOf": "Crypt Worm Anim/Leap/Leap_0002.png",
          "trimmedW": 157,
          "trimmedH": 132,
          "trimmedX": 84,
          "trimmedY": 9,
          "untrimmedW": 308,
          "untrimmedH": 245
        }
      ]
    }
  },
  "atlases": [
    {
      "atlasName": "atlas0",
      "atlasGUID": "172fb1721a80e99479ba9fddfca5c666",
      "atlasPath": "Atlases/Original/Collections/Crypt Worm Cln Data/atlas0.png",
      "width": 1024,
      "height": 1024
    }
  ]
}