{
  "animations": {
    "Beam Wake": {
      "sprites": [
        {
          "name": "Weaver Servitor Anim/Beam Wake/Beam Wake_0000.png",
          "atlasGUID": "d99aad228c3829547b4d57ac2d09df48",
          "x": 0,
          "y": 480,
          "w": 3,
          "h": 5,
          "rotated": false,
          "isDuplicate": false,
          "duplicateOf": "",
          "trimmedW": 3,
          "trimmedH": 5,
          "trimmedX": 121,
          "trimmedY": 261,
          "untrimmedW": 245,
          "untrimmedH": 527
        },
        {
          "name": "Weaver Servitor Anim/Beam Wake/Beam Wake_0001_dup_Beam Wake_0000.png",
          "atlasGUID": "d99aad228c3829547b4d57ac2d09df48",
          "x": 0,
          "y": 480,
          "w": 3,
          "h": 5,
          "rotated": false,
          "isDuplicate": true,
          "duplicateOf": "Weaver Servitor Anim/Beam Wake/Beam Wake_0000.png",
          "trimmedW": 3,
          "trimmedH": 5,
          "trimmedX": 121,
          "trimmedY": 261,
          "untrimmedW": 245,
          "untrimmedH": 527
        },
        {
          "name": "Weaver Servitor Anim/Beam Wake/Beam Wake_0002.png",
          "atlasGUID": "d99aad228c3829547b4d57ac2d09df48",
          "x": 89,
          "y": 397,
          "w": 109,
          "h": 28,
          "rotated": true,
          "isDuplicate": false,
          "duplicateOf": "",
          "trimmedW": 28,
          "trimmedH": 109,
          "trimmedX": 105,
          "trimmedY": 258,
          "untrimmedW": 245,
          "untrimmedH": 527
        },
        {
          "name": "Weaver Servitor Anim/Beam Wake/Beam Wake_0003.png",
          "atlasGUID": "d99aad228c3829547b4d57ac2d09df48",
          "x": 2,
          "y": 440,
          "w": 165,
          "h": 40,
          "rotated": true,
          "isDuplicate": false,
          "duplicateOf": "",
          "trimmedW": 40,
          "trimmedH": 165,
          "trimmedX": 103,
          "trimmedY": 286,
          "untrimmedW": 245,
          "untrimmedH": 527
        }
      ]
    },
    "Beam Walk": {
      "sprites": [
        {
          "name": "Weaver Servitor Anim/Beam Walk/Beam Walk_0000.png",
          "atlasGUID": "d99aad228c3829547b4d57ac2d09df48",
          "x": 2,
          "y": 211,
          "w": 83,
          "h": 225,
          "rotated": false,
          "isDuplicate": false,
          "duplicateOf": "",
          "trimmedW": 83,
          "trimmedH": 225,
          "trimmedX": 84,
          "trimmedY": 276,
          "untrimmedW": 245,
          "untrimmedH": 527
        },
        {
          "name": "Weaver Servitor Anim/Beam Walk/Beam Walk_0001_dup_Beam Walk_0000.png",
          "atlasGUID": "d99aad228c3829547b4d57ac2d09df48",
          "x": 2,
          "y": 211,
          "w": 83,
          "h": 225,
          "rotated": false,
          "isDuplicate": true,
          "duplicateOf": "Weaver Servitor Anim/Beam Walk/Beam Walk_0000.png",
          "trimmedW": 83,
          "trimmedH": 225,
          "trimmedX": 84,
          "trimmedY": 273,
          "untrimmedW": 245,
          "untrimmedH": 527
        },
        {
          "name": "Weaver Servitor Anim/Beam Walk/Beam Walk_0002_dup_Beam Walk_0000.png",
          "atlasGUID": "d99aad228c3829547b4d57ac2d09df48",
          "x": 2,
          "y": 211,
          "w": 83,
          "h": 225,
          "rotated": false,
          "isDuplicate": true,
          "duplicateOf": "Weaver Servitor Anim/Beam Walk/Beam Walk_0000.png",
          "trimmedW": 83,
          "trimmedH": 225,
          "trimmedX": 84,
          "trimmedY": 277,
          "untrimmedW": 245,
          "untrimmedH": 527
        },
        {
          "name": "Weaver Servitor Anim/Beam Walk/Beam Walk_0003_dup_Beam Walk_0000.png",
          "atlasGUID": "d99aad228c3829547b4d57ac2d09df48",
          "x": 2,
          "y": 211,
          "w": 83,
          "h": 225,
          "rotated": false,
          "isDuplicate": true,
          "duplicateOf": "Weaver Servitor Anim/Beam Walk/Beam Walk_0000.png",
          "trimmedW": 83,
          "trimmedH": 225,
          "trimmedX": 84,
          "trimmedY": 278,
          "untrimmedW": 245,
          "untrimmedH": 527
        }
      ]
    },
    "Head Wake": {
      "sprites": [
        {
          "name": "Weaver Servitor Anim/Head Wake/Head Wake_0000.png",
          "atlasGUID": "d99aad228c3829547b4d57ac2d09df48",
          "x": 343,
          "y": 75,
          "w": 65,
          "h": 68,
          "rotated": true,
          "isDuplicate": false,
          "duplicateOf": "",
          "trimmedW": 68,
          "trimmedH": 65,
          "trimmedX": 86,
          "trimmedY": 248,
          "untrimmedW": 245,
          "untrimmedH": 527
        },
        {
          "name": "Weaver Servitor Anim/Head Wake/Head Wake_0001.png",
          "atlasGUID": "d99aad228c3829547b4d57ac2d09df48",
          "x": 274,
          "y": 2,
          "w": 67,
          "h": 69,
          "rotated": true,
          "isDuplicate": false,
          "duplicateOf": "",
          "trimmedW": 69,
          "trimmedH": 67,
          "trimmedX": 86,
          "trimmedY": 242,
          "untrimmedW": 245,
          "untrimmedH": 527
        },
        {
          "name": "Weaver Servitor Anim/Head Wake/Head Wake_0002.png",
          "atlasGUID": "d99aad228c3829547b4d57ac2d09df48",
          "x": 226,
          "y": 282,
          "w": 67,
          "h": 69,
          "rotated": true,
          "isDuplicate": false,
          "duplicateOf": "",
          "trimmedW": 69,
          "trimmedH": 67,
          "trimmedX": 86,
          "trimmedY": 273,
          "untrimmedW": 245,
          "untrimmedH": 527
        },
        {
          "name": "Weaver Servitor Anim/Head Wake/Head Wake_0003.png",
          "atlasGUID": "d99aad228c3829547b4d57ac2d09df48",
          "x": 154,
          "y": 211,
          "w": 68,
          "h": 71,
          "rotated": true,
          "isDuplicate": false,
          "duplicateOf": "",
          "trimmedW": 71,
          "trimmedH": 68,
          "trimmedX": 85,
          "trimmedY": 267,
          "untrimmedW": 245,
          "untrimmedH": 527
        }
      ]
    },
    "Head Walk": {
      "sprites": [
        {
          "name": "Weaver Servitor Anim/Head Walk/Head Walk_0000_dup_Head Wake_0000.png",
          "atlasGUID": "d99aad228c3829547b4d57ac2d09df48",
          "x": 343,
          "y": 75,
          "w": 65,
          "h": 68,
          "rotated": true,
          "isDuplicate": true,
          "duplicateOf": "Weaver Servitor Anim/Head Wake/Head Wake_0000.png",
          "trimmedW": 68,
          "trimmedH": 65,
          "trimmedX": 88,
          "trimmedY": 259,
          "untrimmedW": 245,
          "untrimmedH": 527
        },
        {
          "name": "Weaver Servitor Anim/Head Walk/Head Walk_0001_dup_Head Wake_0000.png",
          "atlasGUID": "d99aad228c3829547b4d57ac2d09df48",
          "x": 343,
          "y": 75,
          "w": 65,
          "h": 68,
          "rotated": true,
          "isDuplicate": true,
          "duplicateOf": "Weaver Servitor Anim/Head Wake/Head Wake_0000.png",
          "trimmedW": 68,
          "trimmedH": 65,
          "trimmedX": 88,
          "trimmedY": 256,
          "untrimmedW": 245,
          "untrimmedH": 527
        },
        {
          "name": "Weaver Servitor Anim/Head Walk/Head Walk_0002_dup_Head Wake_0000.png",
          "atlasGUID": "d99aad228c3829547b4d57ac2d09df48",
          "x": 343,
          "y": 75,
          "w": 65,
          "h": 68,
          "rotated": true,
          "isDuplicate": true,
          "duplicateOf": "Weaver Servitor Anim/Head Wake/Head Wake_0000.png",
          "trimmedW": 68,
          "trimmedH": 65,
          "trimmedX": 88,
          "trimmedY": 259,
          "untrimmedW": 245,
          "untrimmedH": 527
        },
        {
          "name": "Weaver Servitor Anim/Head Walk/Head Walk_0003_dup_Head Wake_0000.png",
          "atlasGUID": "d99aad228c3829547b4d57ac2d09df48",
          "x": 343,
          "y": 75,
          "w": 65,
          "h": 68,
          "rotated": true,
          "isDuplicate": true,
          "duplicateOf": "Weaver Servitor Anim/Head Wake/Head Wake_0000.png",
          "trimmedW": 68,
          "trimmedH": 65,
          "trimmedX": 88,
          "trimmedY": 261,
          "untrimmedW": 245,
          "untrimmedH": 527
        }
      ]
    },
    "Legs Wake": {
      "sprites": [
        {
          "name": "Weaver Servitor Anim/Legs Wake/Legs Wake_0000.png",
          "atlasGUID": "d99aad228c3829547b4d57ac2d09df48",
          "x": 202,
          "y": 152,
          "w": 65,
          "h": 51,
          "rotated": false,
          "isDuplicate": false,
          "duplicateOf": "",
          "trimmedW": 65,
          "trimmedH": 51,
          "trimmedX": 33,
          "trimmedY": 93,
          "untrimmedW": 139,
          "untrimmedH": 293
        },
        {
          "name": "Weaver Servitor Anim/Legs Wake/Legs Wake_0001.png",
          "atlasGUID": "d99aad228c3829547b4d57ac2d09df48",
          "x": 271,
          "y": 152,
          "w": 66,
          "h": 45,
          "rotated": false,
          "isDuplicate": false,
          "duplicateOf": "",
          "trimmedW": 66,
          "trimmedH": 45,
          "trimmedX": 34,
          "trimmedY": 93,
          "untrimmedW": 139,
          "untrimmedH": 293
        },
        {
          "name": "Weaver Servitor Anim/Legs Wake/Legs Wake_0002.png",
          "atlasGUID": "d99aad228c3829547b4d57ac2d09df48",
          "x": 360,
          "y": 275,
          "w": 59,
          "h": 66,
          "rotated": true,
          "isDuplicate": false,
          "duplicateOf": "",
          "trimmedW": 66,
          "trimmedH": 59,
          "trimmedX": 33,
          "trimmedY": 106,
          "untrimmedW": 139,
          "untrimmedH": 293
        },
        {
          "name": "Weaver Servitor Anim/Legs Wake/Legs Wake_0003.png",
          "atlasGUID": "d99aad228c3829547b4d57ac2d09df48",
          "x": 297,
          "y": 275,
          "w": 59,
          "h": 69,
          "rotated": true,
          "isDuplicate": false,
          "duplicateOf": "",
          "trimmedW": 69,
          "trimmedH": 59,
          "trimmedX": 32,
          "trimmedY": 105,
          "untrimmedW": 139,
          "untrimmedH": 293
        }
      ]
    },
    "Legs Walk": {
      "sprites": [
        {
          "name": "Weaver Servitor Anim/Legs Walk/Legs Walk_0000.png",
          "atlasGUID": "d99aad228c3829547b4d57ac2d09df48",
          "x": 264,
          "y": 428,
          "w": 84,
          "h": 58,
          "rotated": false,
          "isDuplicate": false,
          "duplicateOf": "",
          "trimmedW": 84,
          "trimmedH": 58,
          "trimmedX": 26,
          "trimmedY": 95,
          "untrimmedW": 139,
          "untrimmedH": 293
        },
        {
          "name": "Weaver Servitor Anim/Legs Walk/Legs Walk_0001.png",
          "atlasGUID": "d99aad228c3829547b4d57ac2d09df48",
          "x": 171,
          "y": 429,
          "w": 89,
          "h": 57,
          "rotated": false,
          "isDuplicate": false,
          "duplicateOf": "",
          "trimmedW": 89,
          "trimmedH": 57,
          "trimmedX": 27,
          "trimmedY": 95,
          "untrimmedW": 139,
          "untrimmedH": 293
        },
        {
          "name": "Weaver Servitor Anim/Legs Walk/Legs Walk_0002.png",
          "atlasGUID": "d99aad228c3829547b4d57ac2d09df48",
          "x": 89,
          "y": 304,
          "w": 60,
          "h": 89,
          "rotated": true,
          "isDuplicate": false,
          "duplicateOf": "",
          "trimmedW": 89,
          "trimmedH": 60,
          "trimmedX": 26,
          "trimmedY": 95,
          "untrimmedW": 139,
          "untrimmedH": 293
        },
        {
          "name": "Weaver Servitor Anim/Legs Walk/Legs Walk_0003.png",
          "atlasGUID": "d99aad228c3829547b4d57ac2d09df48",
          "x": 89,
          "y": 211,
          "w": 61,
          "h": 89,
          "rotated": true,
          "isDuplicate": false,
          "duplicateOf": "",
          "trimmedW": 89,
          "trimmedH": 61,
          "trimmedX": 22,
          "trimmedY": 94,
          "untrimmedW": 139,
          "untrimmedH": 293
        }
      ]
    },
    "Beam Rest": {
      "sprites": [
        {
          "name": "Weaver Servitor Anim/Beam Rest/Beam Rest_0000_dup_Beam Wake_0003.png",
          "atlasGUID": "d99aad228c3829547b4d57ac2d09df48",
          "x": 2,
          "y": 440,
          "w": 165,
          "h": 40,
          "rotated": true,
          "isDuplicate": true,
          "duplicateOf": "Weaver Servitor Anim/Beam Wake/Beam Wake_0003.png",
          "trimmedW": 40,
          "trimmedH": 165,
          "trimmedX": 103,
          "trimmedY": 286,
          "untrimmedW": 245,
          "untrimmedH": 527
        },
        {
          "name": "Weaver Servitor Anim/Beam Rest/Beam Rest_0001_dup_Beam Wake_0002.png",
          "atlasGUID": "d99aad228c3829547b4d57ac2d09df48",
          "x": 89,
          "y": 397,
          "w": 109,
          "h": 28,
          "rotated": true,
          "isDuplicate": true,
          "duplicateOf": "Weaver Servitor Anim/Beam Wake/Beam Wake_0002.png",
          "trimmedW": 28,
          "trimmedH": 109,
          "trimmedX": 105,
          "trimmedY": 258,
          "untrimmedW": 245,
          "untrimmedH": 527
        },
        {
          "name": "Weaver Servitor Anim/Beam Rest/Beam Rest_0002_dup_Beam Wake_0000.png",
          "atlasGUID": "d99aad228c3829547b4d57ac2d09df48",
          "x": 0,
          "y": 480,
          "w": 3,
          "h": 5,
          "rotated": false,
          "isDuplicate": true,
          "duplicateOf": "Weaver Servitor Anim/Beam Wake/Beam Wake_0000.png",
          "trimmedW": 3,
          "trimmedH": 5,
          "trimmedX": 121,
          "trimmedY": 261,
          "untrimmedW": 245,
          "untrimmedH": 527
        }
      ]
    },
    "Head Rest": {
      "sprites": [
        {
          "name": "Weaver Servitor Anim/Head Rest/Head Rest_0000_dup_Head Wake_0002.png",
          "atlasGUID": "d99aad228c3829547b4d57ac2d09df48",
          "x": 226,
          "y": 282,
          "w": 67,
          "h": 69,
          "rotated": true,
          "isDuplicate": true,
          "duplicateOf": "Weaver Servitor Anim/Head Wake/Head Wake_0002.png",
          "trimmedW": 69,
          "trimmedH": 67,
          "trimmedX": 86,
          "trimmedY": 273,
          "untrimmedW": 245,
          "untrimmedH": 527
        },
        {
          "name": "Weaver Servitor Anim/Head Rest/Head Rest_0001_dup_Head Wake_0001.png",
          "atlasGUID": "d99aad228c3829547b4d57ac2d09df48",
          "x": 274,
          "y": 2,
          "w": 67,
          "h": 69,
          "rotated": true,
          "isDuplicate": true,
          "duplicateOf": "Weaver Servitor Anim/Head Wake/Head Wake_0001.png",
          "trimmedW": 69,
          "trimmedH": 67,
          "trimmedX": 86,
          "trimmedY": 242,
          "untrimmedW": 245,
          "untrimmedH": 527
        },
        {
          "name": "Weaver Servitor Anim/Head Rest/Head Rest_0002_dup_Head Wake_0000.png",
          "atlasGUID": "d99aad228c3829547b4d57ac2d09df48",
          "x": 343,
          "y": 75,
          "w": 65,
          "h": 68,
          "rotated": true,
          "isDuplicate": true,
          "duplicateOf": "Weaver Servitor Anim/Head Wake/Head Wake_0000.png",
          "trimmedW": 68,
          "trimmedH": 65,
          "trimmedX": 86,
          "trimmedY": 248,
          "untrimmedW": 245,
          "untrimmedH": 527
        }
      ]
    },
    "Legs Rest": {
      "sprites": [
        {
          "name": "Weaver Servitor Anim/Legs Rest/Legs Rest_0000_dup_Legs Wake_0002.png",
          "atlasGUID": "d99aad228c3829547b4d57ac2d09df48",
          "x": 360,
          "y": 275,
          "w": 59,
          "h": 66,
          "rotated": true,
          "isDuplicate": true,
          "duplicateOf": "Weaver Servitor Anim/Legs Wake/Legs Wake_0002.png",
          "trimmedW": 66,
          "trimmedH": 59,
          "trimmedX": 33,
          "trimmedY": 106,
          "untrimmedW": 139,
          "untrimmedH": 293
        },
        {
          "name": "Weaver Servitor Anim/Legs Rest/Legs Rest_0001_dup_Legs Wake_0001.png",
          "atlasGUID": "d99aad228c3829547b4d57ac2d09df48",
          "x": 271,
          "y": 152,
          "w": 66,
          "h": 45,
          "rotated": false,
          "isDuplicate": true,
          "duplicateOf": "Weaver Servitor Anim/Legs Wake/Legs Wake_0001.png",
          "trimmedW": 66,
          "trimmedH": 45,
          "trimmedX": 34,
          "trimmedY": 93,
          "untrimmedW": 139,
          "untrimmedH": 293
        },
        {
          "name": "Weaver Servitor Anim/Legs Rest/Legs Rest_0002_dup_Legs Wake_0000.png",
          "atlasGUID": "d99aad228c3829547b4d57ac2d09df48",
          "x": 202,
          "y": 152,
          "w": 65,
          "h": 51,
          "rotated": false,
          "isDuplicate": true,
          "duplicateOf": "Weaver Servitor Anim/Legs Wake/Legs Wake_0000.png",
          "trimmedW": 65,
          "trimmedH": 51,
          "trimmedX": 33,
          "trimmedY": 93,
          "untrimmedW": 139,
          "untrimmedH": 293
        }
      ]
    },
    "Run Away": {
      "sprites": [
        {
          "name": "Weaver Servitor Anim/Run Away/Run Away_0000_dup_Legs Wake_0000.png",
          "atlasGUID": "d99aad228c3829547b4d57ac2d09df48",
          "x": 202,
          "y": 152,
          "w": 65,
          "h": 51,
          "rotated": false,
          "isDuplicate": true,
          "duplicateOf": "Weaver Servitor Anim/Legs Wake/Legs Wake_0000.png",
          "trimmedW": 65,
          "trimmedH": 51,
          "trimmedX": 33,
          "trimmedY": 93,
          "untrimmedW": 139,
          "untrimmedH": 293
        },
        {
          "name": "Weaver Servitor Anim/Run Away/Run Away_0001_dup_Legs Wake_0001.png",
          "atlasGUID": "d99aad228c3829547b4d57ac2d09df48",
          "x": 271,
          "y": 152,
          "w": 66,
          "h": 45,
          "rotated": false,
          "isDuplicate": true,
          "duplicateOf": "Weaver Servitor Anim/Legs Wake/Legs Wake_0001.png",
          "trimmedW": 66,
          "trimmedH": 45,
          "trimmedX": 34,
          "trimmedY": 93,
          "untrimmedW": 139,
          "untrimmedH": 293
        },
        {
          "name": "Weaver Servitor Anim/Run Away/Run Away_0002_dup_Legs Wake_0002.png",
          "atlasGUID": "d99aad228c3829547b4d57ac2d09df48",
          "x": 360,
          "y": 275,
          "w": 59,
          "h": 66,
          "rotated": true,
          "isDuplicate": true,
          "duplicateOf": "Weaver Servitor Anim/Legs Wake/Legs Wake_0002.png",
          "trimmedW": 66,
          "trimmedH": 59,
          "trimmedX": 33,
          "trimmedY": 106,
          "untrimmedW": 139,
          "untrimmedH": 293
        },
        {
          "name": "Weaver Servitor Anim/Run Away/Run Away_0003_dup_Legs Wake_0003.png",
          "atlasGUID": "d99aad228c3829547b4d57ac2d09df48",
          "x": 297,
          "y": 275,
          "w": 59,
          "h": 69,
          "rotated": true,
          "isDuplicate": true,
          "duplicateOf": "Weaver Servitor Anim/Legs Wake/Legs Wake_0003.png",
          "trimmedW": 69,
          "trimmedH": 59,
          "trimmedX": 32,
          "trimmedY": 105,
          "untrimmedW": 139,
          "untrimmedH": 293
        }
      ]
    },
    "Head Wake Moss": {
      "sprites": [
        {
          "name": "Weaver Servitor Anim/Head Wake Moss/Head Wake Moss_0000.png",
          "atlasGUID": "d99aad228c3829547b4d57ac2d09df48",
          "x": 226,
          "y": 207,
          "w": 66,
          "h": 71,
          "rotated": true,
          "isDuplicate": false,
          "duplicateOf": "",
          "trimmedW": 71,
          "trimmedH": 66,
          "trimmedX": 86,
          "trimmedY": 248,
          "untrimmedW": 245,
          "untrimmedH": 527
        },
        {
          "name": "Weaver Servitor Anim/Head Wake Moss/Head Wake Moss_0001.png",
          "atlasGUID": "d99aad228c3829547b4d57ac2d09df48",
          "x": 202,
          "y": 77,
          "w": 67,
          "h": 71,
          "rotated": true,
          "isDuplicate": false,
          "duplicateOf": "",
          "trimmedW": 71,
          "trimmedH": 67,
          "trimmedX": 86,
          "trimmedY": 242,
          "untrimmedW": 245,
          "untrimmedH": 527
        },
        {
          "name": "Weaver Servitor Anim/Head Wake Moss/Head Wake Moss_0002.png",
          "atlasGUID": "d99aad228c3829547b4d57ac2d09df48",
          "x": 202,
          "y": 2,
          "w": 68,
          "h": 71,
          "rotated": true,
          "isDuplicate": false,
          "duplicateOf": "",
          "trimmedW": 71,
          "trimmedH": 68,
          "trimmedX": 86,
          "trimmedY": 273,
          "untrimmedW": 245,
          "untrimmedH": 527
        },
        {
          "name": "Weaver Servitor Anim/Head Wake Moss/Head Wake Moss_0003.png",
          "atlasGUID": "d99aad228c3829547b4d57ac2d09df48",
          "x": 153,
          "y": 304,
          "w": 69,
          "h": 72,
          "rotated": true,
          "isDuplicate": false,
          "duplicateOf": "",
          "trimmedW": 72,
          "trimmedH": 69,
          "trimmedX": 85,
          "trimmedY": 267,
          "untrimmedW": 245,
          "untrimmedH": 527
        }
      ]
    },
    "Head Walk Moss": {
      "sprites": [
        {
          "name": "Weaver Servitor Anim/Head Walk Moss/Head Walk Moss_0000.png",
          "atlasGUID": "d99aad228c3829547b4d57ac2d09df48",
          "x": 274,
          "y": 355,
          "w": 70,
          "h": 66,
          "rotated": false,
          "isDuplicate": false,
          "duplicateOf": "",
          "trimmedW": 70,
          "trimmedH": 66,
          "trimmedX": 88,
          "trimmedY": 259,
          "untrimmedW": 245,
          "untrimmedH": 527
        },
        {
          "name": "Weaver Servitor Anim/Head Walk Moss/Head Walk Moss_0001.png",
          "atlasGUID": "d99aad228c3829547b4d57ac2d09df48",
          "x": 296,
          "y": 201,
          "w": 65,
          "h": 70,
          "rotated": true,
          "isDuplicate": false,
          "duplicateOf": "",
          "trimmedW": 70,
          "trimmedH": 65,
          "trimmedX": 88,
          "trimmedY": 256,
          "untrimmedW": 245,
          "untrimmedH": 527
        },
        {
          "name": "Weaver Servitor Anim/Head Walk Moss/Head Walk Moss_0002_dup_Head Walk Moss_0000.png",
          "atlasGUID": "d99aad228c3829547b4d57ac2d09df48",
          "x": 274,
          "y": 355,
          "w": 70,
          "h": 66,
          "rotated": false,
          "isDuplicate": true,
          "duplicateOf": "Weaver Servitor Anim/Head Walk Moss/Head Walk Moss_0000.png",
          "trimmedW": 70,
          "trimmedH": 66,
          "trimmedX": 88,
          "trimmedY": 259,
          "untrimmedW": 245,
          "untrimmedH": 527
        },
        {
          "name": "Weaver Servitor Anim/Head Walk Moss/Head Walk Moss_0003.png",
          "atlasGUID": "d99aad228c3829547b4d57ac2d09df48",
          "x": 273,
          "y": 77,
          "w": 66,
          "h": 71,
          "rotated": true,
          "isDuplicate": false,
          "duplicateOf": "",
          "trimmedW": 71,
          "trimmedH": 66,
          "trimmedX": 88,
          "trimmedY": 261,
          "untrimmedW": 245,
          "untrimmedH": 527
        }
      ]
    },
    "Head Rest Moss": {
      "sprites": [
        {
          "name": "Weaver Servitor Anim/Head Rest Moss/Head Rest Moss_0000_dup_Head Wake Moss_0002.png",
          "atlasGUID": "d99aad228c3829547b4d57ac2d09df48",
          "x": 202,
          "y": 2,
          "w": 68,
          "h": 71,
          "rotated": true,
          "isDuplicate": true,
          "duplicateOf": "Weaver Servitor Anim/Head Wake Moss/Head Wake Moss_0002.png",
          "trimmedW": 71,
          "trimmedH": 68,
          "trimmedX": 86,
          "trimmedY": 273,
          "untrimmedW": 245,
          "untrimmedH": 527
        },
        {
          "name": "Weaver Servitor Anim/Head Rest Moss/Head Rest Moss_0001_dup_Head Wake Moss_0001.png",
          "atlasGUID": "d99aad228c3829547b4d57ac2d09df48",
          "x": 202,
          "y": 77,
          "w": 67,
          "h": 71,
          "rotated": true,
          "isDuplicate": true,
          "duplicateOf": "Weaver Servitor Anim/Head Wake Moss/Head Wake Moss_0001.png",
          "trimmedW": 71,
          "trimmedH": 67,
          "trimmedX": 86,
          "trimmedY": 242,
          "untrimmedW": 245,
          "untrimmedH": 527
        },
        {
          "name": "Weaver Servitor Anim/Head Rest Moss/Head Rest Moss_0002_dup_Head Wake Moss_0000.png",
          "atlasGUID": "d99aad228c3829547b4d57ac2d09df48",
          "x": 226,
          "y": 207,
          "w": 66,
          "h": 71,
          "rotated": true,
          "isDuplicate": true,
          "duplicateOf": "Weaver Servitor Anim/Head Wake Moss/Head Wake Moss_0000.png",
          "trimmedW": 71,
          "trimmedH": 66,
          "trimmedX": 86,
          "trimmedY": 248,
          "untrimmedW": 245,
          "untrimmedH": 527
        }
      ]
    }
  },
  "atlases": [
    {
      "atlasName": "atlas0",
      "atlasGUID": "d99aad228c3829547b4d57ac2d09df48",
      "atlasPath": "Atlases/Original/Collections/Weaver Servitor Cln Data/atlas0.png",
      "width": 512,
      "height": 512
    }
  ]
}